<didl:DIDL xmlns:didl="urn:mpeg:mpeg21:2002:02-DIDL-NS" xmlns:ddd="http://www.kb.nl/namespaces/ddd" xmlns:dc="http://purl.org/dc/elements/1.1/" xmlns:dcterms="http://purl.org/dc/terms/" xmlns:dcmitype="http://purl.org/dc/dcmitype/" xmlns="urn:mpeg:mpeg21:2002:02-DIDL-NS" xmlns:dcx="http://krait.kb.nl/coop/tel/handbook/telterms.html" xmlns:didmodel="urn:mpeg:mpeg21:2002:02-DIDMODEL-NS" xmlns:srw_dc="info:srw/schema/1/dc-v1.1">
				<didl:Item dc:identifier="ddd:010725323:mpeg21">
					<didl:Component dc:identifier="ddd:010725323:mpeg21:metadata">
						<didl:Descriptor>
							<didl:Statement mimeType="text/plain" dc:type="role">metadata</didl:Statement>
						</didl:Descriptor>
						<didl:Resource mimeType="text/xml">
							<srw_dc:dcx>
								<dc:title>'s Gravenhaegse courant</dc:title>
								<dc:identifier xsi:type="dcx:PPN">832924342</dc:identifier>
								<dc:date>1711-09-14</dc:date>
								<dcterms:temporal>Dag</dcterms:temporal>
								<dcx:recordRights>Koninklijke Bibliotheek Den Haag</dcx:recordRights>
								<dc:publisher>Anthoni Pauw</dc:publisher>
								<dcterms:spatial>Regionaal/lokaal</dcterms:spatial>
								<dc:source>KB C 94</dc:source>
								<dcx:issuenumber>110</dcx:issuenumber>
								<dcx:recordIdentifier>ddd:010725323:mpeg21</dcx:recordIdentifier>
								<dc:identifier>http://resolver.kb.nl/resolve?urn=ddd:010725323:mpeg21</dc:identifier>
								<dc:type xsi:type="dcterms:DCMIType">Text</dc:type>
								<dc:language xsi:type="dcterms:ISO639-1">nl</dc:language>
								<dcterms:isPartOf xsi:type="dcx:collectionIdentifier">DDD</dcterms:isPartOf>
								<dcterms:isPartOf>Databank Digitale Dagbladen</dcterms:isPartOf>
							<ddd:yearsDigitized>1708 t/m 1787</ddd:yearsDigitized><dcterms:spatial xsi:type="dcx:creation">'s-Gravenhage</dcterms:spatial><dcterms:issued>1708-1795</dcterms:issued></srw_dc:dcx>
						</didl:Resource>
					</didl:Component>
					<didl:Component dc:identifier="ddd:010725323:mpeg21:pdf">
						<didl:Descriptor>
							<didl:Statement mimeType="text/plain" dc:type="role">pdf</didl:Statement>
						</didl:Descriptor>
						<didl:Resource mimeType="application/pdf" ref="http://resolver.kb.nl/resolve?urn=ddd:010725323:mpeg21:pdf" dcx:filename="DDD_010725323.pdf" dcx:md5_checksum="493580c1fba0674401e54c34a2e17d9b"/>
					</didl:Component>
					<didl:Item dc:identifier="ddd:010725323:mpeg21:p001">
						<didl:Descriptor>
							<didl:Statement mimeType="text/plain" dc:type="role">page 1</didl:Statement>
						</didl:Descriptor>
						<didl:Component dc:identifier="ddd:010725323:mpeg21:p001:metadata">
							<didl:Descriptor>
								<didl:Statement mimeType="text/plain" dc:type="role">metadata</didl:Statement>
							</didl:Descriptor>
							<didl:Resource mimeType="text/xml">
								<srw_dc:dcx>
									<ddd:nativePageNumber>1</ddd:nativePageNumber>
									<dcx:recordIdentifier>ddd:010725323:mpeg21:p001</dcx:recordIdentifier>
									<dc:identifier>http://resolver.kb.nl/resolve?urn=ddd:010725323:mpeg21:p001</dc:identifier>
									<dc:type xsi:type="dcterms:DCMIType">Text</dc:type>
								<ddd:OCRConfidencelevel>0.631</ddd:OCRConfidencelevel></srw_dc:dcx>
							</didl:Resource>
						</didl:Component>
						<didl:Component dc:identifier="ddd:010725323:mpeg21:p001:image/preservation">
							<didl:Descriptor>
								<didl:Statement mimeType="text/plain" dc:type="role">image/preservation</didl:Statement>
							</didl:Descriptor>
							<didl:Descriptor>
								<didl:Statement mimeType="text/plain" dc:type="technical_targets">targetset_20100707_03</didl:Statement>
							</didl:Descriptor>
							<didl:Resource mimeType="image/jp2" ref="DDD_010725323_001.jp2" dcx:md5_checksum="093683a9340610771387d2de1386c0a2"/>
						</didl:Component>
						<didl:Component dc:identifier="ddd:010725323:mpeg21:p001:metadata/technical">
							<didl:Descriptor>
								<didl:Statement mimeType="text/plain" dc:type="role">metadata/technical</didl:Statement>
							</didl:Descriptor>
							<didl:Resource mimeType="text/xml" ref="DDD_010725323_001_techmeta.xml" dcx:md5_checksum="71a0cb3ae11e89f3994a06d36082239f"/>
						</didl:Component>
						<didl:Component dc:identifier="ddd:010725323:mpeg21:p001:image">
							<didl:Descriptor>
								<didl:Statement mimeType="text/plain" dc:type="role">image</didl:Statement>
							</didl:Descriptor>
							<didl:Resource mimeType="image/jp2" ref="http://resolver.kb.nl/resolve?urn=ddd:010725323:mpeg21:p001:image" dcx:filename="DDD_010725323_001_access.jp2" dcx:md5_checksum="10e503c5e7c1538a4d4e3fcaec2648c3"/>
						</didl:Component>
						<didl:Component dc:identifier="ddd:010725323:mpeg21:p001:alto">
							<didl:Descriptor>
								<didl:Statement mimeType="text/plain" dc:type="role">alto</didl:Statement>
							</didl:Descriptor>
							<didl:Resource mimeType="text/xml" ref="http://resolver.kb.nl/resolve?urn=ddd:010725323:mpeg21:p001:alto" dcx:filename="DDD_010725323_001_alto.xml" dcx:md5_checksum="0eafaa8098356353a9a6605545de5c70"/>
						</didl:Component>
						<didl:Item dc:identifier="ddd:010725323:mpeg21:p001:a0001" ddd:article_id="ddd:010725323:mpeg21:a0001">
							<didl:Component dc:identifier="ddd:010725323:mpeg21:p001:a0001:metadata">
								<didl:Descriptor>
									<didl:Statement mimeType="text/plain" dc:type="role">metadata</didl:Statement>
								</didl:Descriptor>
								<didl:Resource mimeType="text/xml">
									<srw_dc:dcx>
										<dc:subject>artikel</dc:subject>
										<dc:title>SPANJEN.</dc:title>
										<dcterms:accessRights>accessible</dcterms:accessRights>
										<dcx:recordIdentifier>ddd:010725323:mpeg21:a0001</dcx:recordIdentifier>
										<dc:identifier>http://resolver.kb.nl/resolve?urn=ddd:010725323:mpeg21:a0001</dc:identifier>
										<dc:type xsi:type="dcterms:DCMIType">Text</dc:type>
									</srw_dc:dcx>
								</didl:Resource>
							</didl:Component>
							<didl:Component dc:identifier="ddd:010725323:mpeg21:p001:a0001:zoning">
								<didl:Descriptor>
									<didl:Statement mimeType="text/plain" dc:type="role">metadata/zoning</didl:Statement>
								</didl:Descriptor>
								<didl:Resource mimeType="text/xml">
									<dcx:zoning>
										<dcx:coordinates image="DDD_010725323_001_access.jp2">
											<dcx:area hpos="322" vpos="600" width="392" height="40"/>
											<dcx:area hpos="47" vpos="605" width="961" height="1407"/>
										</dcx:coordinates>
									</dcx:zoning>
								</didl:Resource>
							</didl:Component>
						</didl:Item>
						<didl:Item dc:identifier="ddd:010725323:mpeg21:p001:a0002" ddd:article_id="ddd:010725323:mpeg21:a0002">
							<didl:Component dc:identifier="ddd:010725323:mpeg21:p001:a0002:metadata">
								<didl:Descriptor>
									<didl:Statement mimeType="text/plain" dc:type="role">metadata</didl:Statement>
								</didl:Descriptor>
								<didl:Resource mimeType="text/xml">
									<srw_dc:dcx>
										<dc:subject>artikel</dc:subject>
										<dc:title>DUYTSLAND en d'aengrenzende RYKEN.</dc:title>
										<dcterms:accessRights>accessible</dcterms:accessRights>
										<dcx:recordIdentifier>ddd:010725323:mpeg21:a0002</dcx:recordIdentifier>
										<dc:identifier>http://resolver.kb.nl/resolve?urn=ddd:010725323:mpeg21:a0002</dc:identifier>
										<dc:type xsi:type="dcterms:DCMIType">Text</dc:type>
									</srw_dc:dcx>
								</didl:Resource>
							</didl:Component>
							<didl:Component dc:identifier="ddd:010725323:mpeg21:p001:a0002:zoning">
								<didl:Descriptor>
									<didl:Statement mimeType="text/plain" dc:type="role">metadata/zoning</didl:Statement>
								</didl:Descriptor>
								<didl:Resource mimeType="text/xml">
									<dcx:zoning>
										<dcx:coordinates image="DDD_010725323_001_access.jp2">
											<dcx:area hpos="116" vpos="2017" width="807" height="34"/>
											<dcx:area hpos="53" vpos="2059" width="946" height="1618"/>
										</dcx:coordinates>
									</dcx:zoning>
								</didl:Resource>
							</didl:Component>
						</didl:Item>
						<didl:Item dc:identifier="ddd:010725323:mpeg21:p001:a0003" ddd:article_id="ddd:010725323:mpeg21:a0003">
							<didl:Component dc:identifier="ddd:010725323:mpeg21:p001:a0003:metadata">
								<didl:Descriptor>
									<didl:Statement mimeType="text/plain" dc:type="role">metadata</didl:Statement>
								</didl:Descriptor>
								<didl:Resource mimeType="text/xml">
									<srw_dc:dcx>
										<dc:subject>artikel</dc:subject>
										<dc:title>GROOT-BRITTANNIEN.</dc:title>
										<dcterms:accessRights>accessible</dcterms:accessRights>
										<dcx:recordIdentifier>ddd:010725323:mpeg21:a0003</dcx:recordIdentifier>
										<dc:identifier>http://resolver.kb.nl/resolve?urn=ddd:010725323:mpeg21:a0003</dc:identifier>
										<dc:type xsi:type="dcterms:DCMIType">Text</dc:type>
									</srw_dc:dcx>
								</didl:Resource>
							</didl:Component>
							<didl:Component dc:identifier="ddd:010725323:mpeg21:p001:a0003:zoning">
								<didl:Descriptor>
									<didl:Statement mimeType="text/plain" dc:type="role">metadata/zoning</didl:Statement>
								</didl:Descriptor>
								<didl:Resource mimeType="text/xml">
									<dcx:zoning>
										<dcx:coordinates image="DDD_010725323_001_access.jp2">
											<dcx:area hpos="178" vpos="3686" width="689" height="28"/>
											<dcx:area hpos="53" vpos="3724" width="940" height="106"/>
											<dcx:area hpos="1023" vpos="598" width="953" height="1245"/>
										</dcx:coordinates>
									</dcx:zoning>
								</didl:Resource>
							</didl:Component>
						</didl:Item>
						<didl:Item dc:identifier="ddd:010725323:mpeg21:p001:a0004" ddd:article_id="ddd:010725323:mpeg21:a0004">
							<didl:Component dc:identifier="ddd:010725323:mpeg21:p001:a0004:metadata">
								<didl:Descriptor>
									<didl:Statement mimeType="text/plain" dc:type="role">metadata</didl:Statement>
								</didl:Descriptor>
								<didl:Resource mimeType="text/xml">
									<srw_dc:dcx>
										<dc:subject>artikel</dc:subject>
										<dc:title>NEDERLANDEN.</dc:title>
										<dcterms:accessRights>accessible</dcterms:accessRights>
										<dcx:recordIdentifier>ddd:010725323:mpeg21:a0004</dcx:recordIdentifier>
										<dc:identifier>http://resolver.kb.nl/resolve?urn=ddd:010725323:mpeg21:a0004</dc:identifier>
										<dc:type xsi:type="dcterms:DCMIType">Text</dc:type>
									</srw_dc:dcx>
								</didl:Resource>
							</didl:Component>
							<didl:Component dc:identifier="ddd:010725323:mpeg21:p001:a0004:zoning">
								<didl:Descriptor>
									<didl:Statement mimeType="text/plain" dc:type="role">metadata/zoning</didl:Statement>
								</didl:Descriptor>
								<didl:Resource mimeType="text/xml">
									<dcx:zoning>
										<dcx:coordinates image="DDD_010725323_001_access.jp2">
											<dcx:area hpos="1212" vpos="1853" width="559" height="33"/>
											<dcx:area hpos="1030" vpos="1894" width="950" height="1937"/>
										</dcx:coordinates>
									</dcx:zoning>
								</didl:Resource>
							</didl:Component>
						</didl:Item>
					</didl:Item>
					<didl:Item dc:identifier="ddd:010725323:mpeg21:p002">
						<didl:Descriptor>
							<didl:Statement mimeType="text/plain" dc:type="role">page 2</didl:Statement>
						</didl:Descriptor>
						<didl:Component dc:identifier="ddd:010725323:mpeg21:p002:metadata">
							<didl:Descriptor>
								<didl:Statement mimeType="text/plain" dc:type="role">metadata</didl:Statement>
							</didl:Descriptor>
							<didl:Resource mimeType="text/xml">
								<srw_dc:dcx>
									<ddd:nativePageNumber>2</ddd:nativePageNumber>
									<dcx:recordIdentifier>ddd:010725323:mpeg21:p002</dcx:recordIdentifier>
									<dc:identifier>http://resolver.kb.nl/resolve?urn=ddd:010725323:mpeg21:p002</dc:identifier>
									<dc:type xsi:type="dcterms:DCMIType">Text</dc:type>
								<ddd:OCRConfidencelevel>0.637</ddd:OCRConfidencelevel></srw_dc:dcx>
							</didl:Resource>
						</didl:Component>
						<didl:Component dc:identifier="ddd:010725323:mpeg21:p002:image/preservation">
							<didl:Descriptor>
								<didl:Statement mimeType="text/plain" dc:type="role">image/preservation</didl:Statement>
							</didl:Descriptor>
							<didl:Descriptor>
								<didl:Statement mimeType="text/plain" dc:type="technical_targets">targetset_20100707_03</didl:Statement>
							</didl:Descriptor>
							<didl:Resource mimeType="image/jp2" ref="DDD_010725323_002.jp2" dcx:md5_checksum="4fb9a9d14d189fa1b9a8f37f7825b790"/>
						</didl:Component>
						<didl:Component dc:identifier="ddd:010725323:mpeg21:p002:metadata/technical">
							<didl:Descriptor>
								<didl:Statement mimeType="text/plain" dc:type="role">metadata/technical</didl:Statement>
							</didl:Descriptor>
							<didl:Resource mimeType="text/xml" ref="DDD_010725323_002_techmeta.xml" dcx:md5_checksum="00cf4fb0c2c99592366a255a001036f2"/>
						</didl:Component>
						<didl:Component dc:identifier="ddd:010725323:mpeg21:p002:image">
							<didl:Descriptor>
								<didl:Statement mimeType="text/plain" dc:type="role">image</didl:Statement>
							</didl:Descriptor>
							<didl:Resource mimeType="image/jp2" ref="http://resolver.kb.nl/resolve?urn=ddd:010725323:mpeg21:p002:image" dcx:filename="DDD_010725323_002_access.jp2" dcx:md5_checksum="669428e51e12da29e0f6bb77df1de99d"/>
						</didl:Component>
						<didl:Component dc:identifier="ddd:010725323:mpeg21:p002:alto">
							<didl:Descriptor>
								<didl:Statement mimeType="text/plain" dc:type="role">alto</didl:Statement>
							</didl:Descriptor>
							<didl:Resource mimeType="text/xml" ref="http://resolver.kb.nl/resolve?urn=ddd:010725323:mpeg21:p002:alto" dcx:filename="DDD_010725323_002_alto.xml" dcx:md5_checksum="239fb75b4b1b0fe6caacccc0d77fe4cf"/>
						</didl:Component>
						<didl:Item dc:identifier="ddd:010725323:mpeg21:p002:a0001" ddd:article_id="ddd:010725323:mpeg21:a0004">
							<didl:Component dc:identifier="ddd:010725323:mpeg21:p002:a0001:metadata">
								<didl:Descriptor>
									<didl:Statement mimeType="text/plain" dc:type="role">metadata</didl:Statement>
								</didl:Descriptor>
								<didl:Resource mimeType="text/xml">
									<srw_dc:dcx>
										<dc:subject>artikel</dc:subject>
										<dc:title>NEDERLANDEN.</dc:title>
										<dcterms:accessRights>accessible</dcterms:accessRights>
										<dcx:recordIdentifier>ddd:010725323:mpeg21:a0004</dcx:recordIdentifier>
										<dc:identifier>http://resolver.kb.nl/resolve?urn=ddd:010725323:mpeg21:a0004</dc:identifier>
										<dc:type xsi:type="dcterms:DCMIType">Text</dc:type>
									</srw_dc:dcx>
								</didl:Resource>
							</didl:Component>
							<didl:Component dc:identifier="ddd:010725323:mpeg21:p002:a0001:zoning">
								<didl:Descriptor>
									<didl:Statement mimeType="text/plain" dc:type="role">metadata/zoning</didl:Statement>
								</didl:Descriptor>
								<didl:Resource mimeType="text/xml">
									<dcx:zoning>
										<dcx:coordinates image="DDD_010725323_002_access.jp2">
											<dcx:area hpos="51" vpos="60" width="969" height="2662"/>
											<dcx:area hpos="1018" vpos="57" width="969" height="2663"/>
										</dcx:coordinates>
									</dcx:zoning>
								</didl:Resource>
							</didl:Component>
						</didl:Item>
						<didl:Item dc:identifier="ddd:010725323:mpeg21:p002:a0002" ddd:article_id="ddd:010725323:mpeg21:a0005">
							<didl:Component dc:identifier="ddd:010725323:mpeg21:p002:a0002:metadata">
								<didl:Descriptor>
									<didl:Statement mimeType="text/plain" dc:type="role">metadata</didl:Statement>
								</didl:Descriptor>
								<didl:Resource mimeType="text/xml">
									<srw_dc:dcx>
										<dc:subject>advertentie</dc:subject>
										<dc:title>Advertentie</dc:title>
										<dcterms:accessRights>accessible</dcterms:accessRights>
										<dcx:recordIdentifier>ddd:010725323:mpeg21:a0005</dcx:recordIdentifier>
										<dc:identifier>http://resolver.kb.nl/resolve?urn=ddd:010725323:mpeg21:a0005</dc:identifier>
										<dc:type xsi:type="dcterms:DCMIType">Text</dc:type>
									</srw_dc:dcx>
								</didl:Resource>
							</didl:Component>
							<didl:Component dc:identifier="ddd:010725323:mpeg21:p002:a0002:zoning">
								<didl:Descriptor>
									<didl:Statement mimeType="text/plain" dc:type="role">metadata/zoning</didl:Statement>
								</didl:Descriptor>
								<didl:Resource mimeType="text/xml">
									<dcx:zoning>
										<dcx:coordinates image="DDD_010725323_002_access.jp2">
											<dcx:area hpos="56" vpos="2727" width="1919" height="1037"/>
										</dcx:coordinates>
									</dcx:zoning>
								</didl:Resource>
							</didl:Component>
						</didl:Item>
					</didl:Item>
					<didl:Item dc:identifier="ddd:010725323:mpeg21:a0001">
						<didl:Descriptor>
							<didl:Statement mimeType="text/plain" dc:type="role">article 1</didl:Statement>
						</didl:Descriptor>
						<didl:Component dc:identifier="ddd:010725323:mpeg21:a0001:ocr">
							<didl:Descriptor>
								<didl:Statement mimeType="text/plain" dc:type="role">ocr</didl:Statement>
							</didl:Descriptor>
							<didl:Resource mimeType="text/xml" ref="http://resolver.kb.nl/resolve?urn=ddd:010725323:mpeg21:a0001:ocr" dcx:filename="DDD_010725323_0001_articletext.xml" dcx:md5_checksum="b2f8cdb329bbdb3b52ec8a699166899e"/>
						</didl:Component>
						<didl:Component dc:identifier="ddd:010725323:mpeg21:a0001:metadata">
							<didl:Descriptor>
								<didl:Statement mimeType="text/plain" dc:type="role">metadata</didl:Statement>
							</didl:Descriptor>
							<didl:Resource mimeType="text/xml">
								<srw_dc:dcx>
									<dc:subject>artikel</dc:subject>
									<dc:title>SPANJEN.</dc:title>
									<dcterms:accessRights>accessible</dcterms:accessRights>
									<dcx:recordIdentifier>ddd:010725323:mpeg21:a0001</dcx:recordIdentifier>
									<dc:identifier>http://resolver.kb.nl/resolve?urn=ddd:010725323:mpeg21:a0001</dc:identifier>
									<dc:type xsi:type="dcterms:DCMIType">Text</dc:type>
								</srw_dc:dcx>
							</didl:Resource>
						</didl:Component>
						<didl:Component dc:identifier="ddd:010725323:mpeg21:a0001:zoning">
							<didl:Descriptor>
								<didl:Statement mimeType="text/plain" dc:type="role">metadata/zoning</didl:Statement>
							</didl:Descriptor>
							<didl:Resource mimeType="text/xml">
								<dcx:zoning>
									<dcx:article-part order="1" pageid="ddd:010725323:mpeg21:p001">
										<dcx:coordinates image="DDD_010725323_001_access.jp2">
											<dcx:area hpos="322" vpos="600" width="392" height="40"/>
											<dcx:area hpos="47" vpos="605" width="961" height="1407"/>
										</dcx:coordinates>
										<dcx:blocks alto="DDD_010725323_001_alto.xml">
											<dcx:TextBlock ID="P1_TB00004"/>
											<dcx:TextBlock ID="P1_TB00005"/>
										</dcx:blocks>
									</dcx:article-part>
								</dcx:zoning>
							</didl:Resource>
						</didl:Component>
					</didl:Item>
					<didl:Item dc:identifier="ddd:010725323:mpeg21:a0002">
						<didl:Descriptor>
							<didl:Statement mimeType="text/plain" dc:type="role">article 2</didl:Statement>
						</didl:Descriptor>
						<didl:Component dc:identifier="ddd:010725323:mpeg21:a0002:ocr">
							<didl:Descriptor>
								<didl:Statement mimeType="text/plain" dc:type="role">ocr</didl:Statement>
							</didl:Descriptor>
							<didl:Resource mimeType="text/xml" ref="http://resolver.kb.nl/resolve?urn=ddd:010725323:mpeg21:a0002:ocr" dcx:filename="DDD_010725323_0002_articletext.xml" dcx:md5_checksum="32e5954abd1519b7b4e1d92cc35d4da0"/>
						</didl:Component>
						<didl:Component dc:identifier="ddd:010725323:mpeg21:a0002:metadata">
							<didl:Descriptor>
								<didl:Statement mimeType="text/plain" dc:type="role">metadata</didl:Statement>
							</didl:Descriptor>
							<didl:Resource mimeType="text/xml">
								<srw_dc:dcx>
									<dc:subject>artikel</dc:subject>
									<dc:title>DUYTSLAND en d'aengrenzende RYKEN.</dc:title>
									<dcterms:accessRights>accessible</dcterms:accessRights>
									<dcx:recordIdentifier>ddd:010725323:mpeg21:a0002</dcx:recordIdentifier>
									<dc:identifier>http://resolver.kb.nl/resolve?urn=ddd:010725323:mpeg21:a0002</dc:identifier>
									<dc:type xsi:type="dcterms:DCMIType">Text</dc:type>
								</srw_dc:dcx>
							</didl:Resource>
						</didl:Component>
						<didl:Component dc:identifier="ddd:010725323:mpeg21:a0002:zoning">
							<didl:Descriptor>
								<didl:Statement mimeType="text/plain" dc:type="role">metadata/zoning</didl:Statement>
							</didl:Descriptor>
							<didl:Resource mimeType="text/xml">
								<dcx:zoning>
									<dcx:article-part order="1" pageid="ddd:010725323:mpeg21:p001">
										<dcx:coordinates image="DDD_010725323_001_access.jp2">
											<dcx:area hpos="116" vpos="2017" width="807" height="34"/>
											<dcx:area hpos="53" vpos="2059" width="946" height="1618"/>
										</dcx:coordinates>
										<dcx:blocks alto="DDD_010725323_001_alto.xml">
											<dcx:TextBlock ID="P1_TB00006"/>
											<dcx:TextBlock ID="P1_TB00007"/>
										</dcx:blocks>
									</dcx:article-part>
								</dcx:zoning>
							</didl:Resource>
						</didl:Component>
					</didl:Item>
					<didl:Item dc:identifier="ddd:010725323:mpeg21:a0003">
						<didl:Descriptor>
							<didl:Statement mimeType="text/plain" dc:type="role">article 3</didl:Statement>
						</didl:Descriptor>
						<didl:Component dc:identifier="ddd:010725323:mpeg21:a0003:ocr">
							<didl:Descriptor>
								<didl:Statement mimeType="text/plain" dc:type="role">ocr</didl:Statement>
							</didl:Descriptor>
							<didl:Resource mimeType="text/xml" ref="http://resolver.kb.nl/resolve?urn=ddd:010725323:mpeg21:a0003:ocr" dcx:filename="DDD_010725323_0003_articletext.xml" dcx:md5_checksum="93d0e3e8504e2f627b278f675cf2112a"/>
						</didl:Component>
						<didl:Component dc:identifier="ddd:010725323:mpeg21:a0003:metadata">
							<didl:Descriptor>
								<didl:Statement mimeType="text/plain" dc:type="role">metadata</didl:Statement>
							</didl:Descriptor>
							<didl:Resource mimeType="text/xml">
								<srw_dc:dcx>
									<dc:subject>artikel</dc:subject>
									<dc:title>GROOT-BRITTANNIEN.</dc:title>
									<dcterms:accessRights>accessible</dcterms:accessRights>
									<dcx:recordIdentifier>ddd:010725323:mpeg21:a0003</dcx:recordIdentifier>
									<dc:identifier>http://resolver.kb.nl/resolve?urn=ddd:010725323:mpeg21:a0003</dc:identifier>
									<dc:type xsi:type="dcterms:DCMIType">Text</dc:type>
								</srw_dc:dcx>
							</didl:Resource>
						</didl:Component>
						<didl:Component dc:identifier="ddd:010725323:mpeg21:a0003:zoning">
							<didl:Descriptor>
								<didl:Statement mimeType="text/plain" dc:type="role">metadata/zoning</didl:Statement>
							</didl:Descriptor>
							<didl:Resource mimeType="text/xml">
								<dcx:zoning>
									<dcx:article-part order="1" pageid="ddd:010725323:mpeg21:p001">
										<dcx:coordinates image="DDD_010725323_001_access.jp2">
											<dcx:area hpos="178" vpos="3686" width="689" height="28"/>
											<dcx:area hpos="53" vpos="3724" width="940" height="106"/>
											<dcx:area hpos="1023" vpos="598" width="953" height="1245"/>
										</dcx:coordinates>
										<dcx:blocks alto="DDD_010725323_001_alto.xml">
											<dcx:TextBlock ID="P1_TB00008"/>
											<dcx:TextBlock ID="P1_TB00009"/>
											<dcx:TextBlock ID="P1_TB00010"/>
										</dcx:blocks>
									</dcx:article-part>
								</dcx:zoning>
							</didl:Resource>
						</didl:Component>
					</didl:Item>
					<didl:Item dc:identifier="ddd:010725323:mpeg21:a0004">
						<didl:Descriptor>
							<didl:Statement mimeType="text/plain" dc:type="role">article 4</didl:Statement>
						</didl:Descriptor>
						<didl:Component dc:identifier="ddd:010725323:mpeg21:a0004:ocr">
							<didl:Descriptor>
								<didl:Statement mimeType="text/plain" dc:type="role">ocr</didl:Statement>
							</didl:Descriptor>
							<didl:Resource mimeType="text/xml" ref="http://resolver.kb.nl/resolve?urn=ddd:010725323:mpeg21:a0004:ocr" dcx:filename="DDD_010725323_0004_articletext.xml" dcx:md5_checksum="5097f56fce03891bfa456c3d6453a04c"/>
						</didl:Component>
						<didl:Component dc:identifier="ddd:010725323:mpeg21:a0004:metadata">
							<didl:Descriptor>
								<didl:Statement mimeType="text/plain" dc:type="role">metadata</didl:Statement>
							</didl:Descriptor>
							<didl:Resource mimeType="text/xml">
								<srw_dc:dcx>
									<dc:subject>artikel</dc:subject>
									<dc:title>NEDERLANDEN.</dc:title>
									<dcterms:accessRights>accessible</dcterms:accessRights>
									<dcx:recordIdentifier>ddd:010725323:mpeg21:a0004</dcx:recordIdentifier>
									<dc:identifier>http://resolver.kb.nl/resolve?urn=ddd:010725323:mpeg21:a0004</dc:identifier>
									<dc:type xsi:type="dcterms:DCMIType">Text</dc:type>
								</srw_dc:dcx>
							</didl:Resource>
						</didl:Component>
						<didl:Component dc:identifier="ddd:010725323:mpeg21:a0004:zoning">
							<didl:Descriptor>
								<didl:Statement mimeType="text/plain" dc:type="role">metadata/zoning</didl:Statement>
							</didl:Descriptor>
							<didl:Resource mimeType="text/xml">
								<dcx:zoning>
									<dcx:article-part order="1" pageid="ddd:010725323:mpeg21:p001">
										<dcx:coordinates image="DDD_010725323_001_access.jp2">
											<dcx:area hpos="1212" vpos="1853" width="559" height="33"/>
											<dcx:area hpos="1030" vpos="1894" width="950" height="1937"/>
										</dcx:coordinates>
										<dcx:blocks alto="DDD_010725323_001_alto.xml">
											<dcx:TextBlock ID="P1_TB00011"/>
											<dcx:TextBlock ID="P1_TB00012"/>
										</dcx:blocks>
									</dcx:article-part>
									<dcx:article-part order="2" pageid="ddd:010725323:mpeg21:p002">
										<dcx:coordinates image="DDD_010725323_002_access.jp2">
											<dcx:area hpos="51" vpos="60" width="969" height="2662"/>
											<dcx:area hpos="1018" vpos="57" width="969" height="2663"/>
										</dcx:coordinates>
										<dcx:blocks alto="DDD_010725323_002_alto.xml">
											<dcx:TextBlock ID="P2_TB00001"/>
											<dcx:TextBlock ID="P2_TB00002"/>
										</dcx:blocks>
									</dcx:article-part>
								</dcx:zoning>
							</didl:Resource>
						</didl:Component>
					</didl:Item>
					<didl:Item dc:identifier="ddd:010725323:mpeg21:a0005">
						<didl:Descriptor>
							<didl:Statement mimeType="text/plain" dc:type="role">article 5</didl:Statement>
						</didl:Descriptor>
						<didl:Component dc:identifier="ddd:010725323:mpeg21:a0005:ocr">
							<didl:Descriptor>
								<didl:Statement mimeType="text/plain" dc:type="role">ocr</didl:Statement>
							</didl:Descriptor>
							<didl:Resource mimeType="text/xml" ref="http://resolver.kb.nl/resolve?urn=ddd:010725323:mpeg21:a0005:ocr" dcx:filename="DDD_010725323_0005_articletext.xml" dcx:md5_checksum="ad8aac7c5cb76408d12575249e5a74d3"/>
						</didl:Component>
						<didl:Component dc:identifier="ddd:010725323:mpeg21:a0005:metadata">
							<didl:Descriptor>
								<didl:Statement mimeType="text/plain" dc:type="role">metadata</didl:Statement>
							</didl:Descriptor>
							<didl:Resource mimeType="text/xml">
								<srw_dc:dcx>
									<dc:subject>advertentie</dc:subject>
									<dc:title>Advertentie</dc:title>
									<dcterms:accessRights>accessible</dcterms:accessRights>
									<dcx:recordIdentifier>ddd:010725323:mpeg21:a0005</dcx:recordIdentifier>
									<dc:identifier>http://resolver.kb.nl/resolve?urn=ddd:010725323:mpeg21:a0005</dc:identifier>
									<dc:type xsi:type="dcterms:DCMIType">Text</dc:type>
								</srw_dc:dcx>
							</didl:Resource>
						</didl:Component>
						<didl:Component dc:identifier="ddd:010725323:mpeg21:a0005:zoning">
							<didl:Descriptor>
								<didl:Statement mimeType="text/plain" dc:type="role">metadata/zoning</didl:Statement>
							</didl:Descriptor>
							<didl:Resource mimeType="text/xml">
								<dcx:zoning>
									<dcx:article-part order="1" pageid="ddd:010725323:mpeg21:p002">
										<dcx:coordinates image="DDD_010725323_002_access.jp2">
											<dcx:area hpos="56" vpos="2727" width="1919" height="1037"/>
										</dcx:coordinates>
										<dcx:blocks alto="DDD_010725323_002_alto.xml">
											<dcx:TextBlock ID="P2_TB00003"/>
										</dcx:blocks>
									</dcx:article-part>
								</dcx:zoning>
							</didl:Resource>
						</didl:Component>
					</didl:Item>
				</didl:Item>
			</didl:DIDL>