<didl:DIDL xmlns:didl="urn:mpeg:mpeg21:2002:02-DIDL-NS" xmlns:ddd="http://www.kb.nl/namespaces/ddd" xmlns:dc="http://purl.org/dc/elements/1.1/" xmlns:dcterms="http://purl.org/dc/terms/" xmlns:dcmitype="http://purl.org/dc/dcmitype/" xmlns="urn:mpeg:mpeg21:2002:02-DIDL-NS" xmlns:dcx="http://krait.kb.nl/coop/tel/handbook/telterms.html" xmlns:didmodel="urn:mpeg:mpeg21:2002:02-DIDMODEL-NS" xmlns:srw_dc="info:srw/schema/1/dc-v1.1">
				<didl:Item dc:identifier="ddd:011228128:mpeg21">
					<didl:Component dc:identifier="ddd:011228128:mpeg21:metadata">
						<didl:Descriptor>
							<didl:Statement mimeType="text/plain" dc:type="role">metadata</didl:Statement>
						</didl:Descriptor>
						<didl:Resource mimeType="text/xml">
							<srw_dc:dcx>
								<dc:title>Oprechte Haerlemsche courant</dc:title>
								<dc:identifier xsi:type="dcx:PPN">841198969</dc:identifier>
								<dcterms:alternative>Eerder verschenen onder de naam Haerlemse courante</dcterms:alternative>
								<dcterms:isVersionOf>Haerlemse courante</dcterms:isVersionOf>
								<dc:date>1710-03-15</dc:date>
								<dcterms:temporal>Dag</dcterms:temporal>
								<dcx:recordRights>Koninklijke Bibliotheek Den Haag</dcx:recordRights>
								<dc:publisher>Abraham Casteleyn</dc:publisher>
								<dcterms:spatial>Landelijk</dcterms:spatial>
								<dc:source>Koninklijke Bibliotheek C 37</dc:source>
								<dcx:issuenumber>11</dcx:issuenumber>
								<dcx:recordIdentifier>ddd:011228128:mpeg21</dcx:recordIdentifier>
								<dc:identifier>http://resolver.kb.nl/resolve?urn=ddd:011228128:mpeg21</dc:identifier>
								<dc:type xsi:type="dcterms:DCMIType">Text</dc:type>
								<dc:language xsi:type="dcterms:ISO639-1">nl</dc:language>
								<dcterms:isPartOf xsi:type="dcx:collectionIdentifier">DDD</dcterms:isPartOf>
								<dcterms:isPartOf>Databank Digitale Dagbladen</dcterms:isPartOf>
							<ddd:yearsDigitized>1662-1795</ddd:yearsDigitized><dcterms:spatial xsi:type="dcx:creation">Haerlem</dcterms:spatial><dcterms:issued>1662-1795</dcterms:issued></srw_dc:dcx>
						</didl:Resource>
					</didl:Component>
					<didl:Component dc:identifier="ddd:011228128:mpeg21:pdf">
						<didl:Descriptor>
							<didl:Statement mimeType="text/plain" dc:type="role">pdf</didl:Statement>
						</didl:Descriptor>
						<didl:Resource mimeType="application/pdf" ref="http://resolver.kb.nl/resolve?urn=ddd:011228128:mpeg21:pdf" dcx:filename="DDD_011228128.pdf" dcx:md5_checksum="c2eb3b45b2f1f77e4c6ab233c7e4b089"/>
					</didl:Component>
					<didl:Item dc:identifier="ddd:011228128:mpeg21:p001">
						<didl:Descriptor>
							<didl:Statement mimeType="text/plain" dc:type="role">page 1</didl:Statement>
						</didl:Descriptor>
						<didl:Component dc:identifier="ddd:011228128:mpeg21:p001:metadata">
							<didl:Descriptor>
								<didl:Statement mimeType="text/plain" dc:type="role">metadata</didl:Statement>
							</didl:Descriptor>
							<didl:Resource mimeType="text/xml">
								<srw_dc:dcx>
									<ddd:nativePageNumber>1</ddd:nativePageNumber>
									<dcx:recordIdentifier>ddd:011228128:mpeg21:p001</dcx:recordIdentifier>
									<dc:identifier>http://resolver.kb.nl/resolve?urn=ddd:011228128:mpeg21:p001</dc:identifier>
									<dc:type xsi:type="dcterms:DCMIType">Text</dc:type>
								<ddd:OCRConfidencelevel>0.608</ddd:OCRConfidencelevel></srw_dc:dcx>
							</didl:Resource>
						</didl:Component>
						<didl:Component dc:identifier="ddd:011228128:mpeg21:p001:image/preservation">
							<didl:Descriptor>
								<didl:Statement mimeType="text/plain" dc:type="role">image/preservation</didl:Statement>
							</didl:Descriptor>
							<didl:Resource mimeType="image/jp2" ref="DDD_011228128_001.jp2" dcx:md5_checksum="ba5e9c161c6eb669d4979859c6185262"/>
						</didl:Component>
						<didl:Component dc:identifier="ddd:011228128:mpeg21:p001:metadata/technical">
							<didl:Descriptor>
								<didl:Statement mimeType="text/plain" dc:type="role">metadata/technical</didl:Statement>
							</didl:Descriptor>
							<didl:Resource mimeType="text/xml" ref="DDD_011228128_001_techmeta.xml" dcx:md5_checksum="7808c10897680904e90c985ec6a030b2"/>
						</didl:Component>
						<didl:Component dc:identifier="ddd:011228128:mpeg21:p001:image">
							<didl:Descriptor>
								<didl:Statement mimeType="text/plain" dc:type="role">image</didl:Statement>
							</didl:Descriptor>
							<didl:Resource mimeType="image/jp2" ref="http://resolver.kb.nl/resolve?urn=ddd:011228128:mpeg21:p001:image" dcx:filename="DDD_011228128_001_access.jp2" dcx:md5_checksum="12bd5f2a6be9e7aa065e62ff391300f6"/>
						</didl:Component>
						<didl:Component dc:identifier="ddd:011228128:mpeg21:p001:alto">
							<didl:Descriptor>
								<didl:Statement mimeType="text/plain" dc:type="role">alto</didl:Statement>
							</didl:Descriptor>
							<didl:Resource mimeType="text/xml" ref="http://resolver.kb.nl/resolve?urn=ddd:011228128:mpeg21:p001:alto" dcx:filename="DDD_011228128_001_alto.xml" dcx:md5_checksum="d4c4cf77999fd6363f831d2ecbc6582a"/>
						</didl:Component>
						<didl:Item dc:identifier="ddd:011228128:mpeg21:p001:a0001" ddd:article_id="ddd:011228128:mpeg21:a0001">
							<didl:Component dc:identifier="ddd:011228128:mpeg21:p001:a0001:metadata">
								<didl:Descriptor>
									<didl:Statement mimeType="text/plain" dc:type="role">metadata</didl:Statement>
								</didl:Descriptor>
								<didl:Resource mimeType="text/xml">
									<srw_dc:dcx>
										<dc:subject>artikel</dc:subject>
										<dc:title>TURCKYEN</dc:title>
										<dcterms:accessRights>accessible</dcterms:accessRights>
										<dcx:recordIdentifier>ddd:011228128:mpeg21:a0001</dcx:recordIdentifier>
										<dc:identifier>http://resolver.kb.nl/resolve?urn=ddd:011228128:mpeg21:a0001</dc:identifier>
										<dc:type xsi:type="dcterms:DCMIType">Text</dc:type>
									</srw_dc:dcx>
								</didl:Resource>
							</didl:Component>
							<didl:Component dc:identifier="ddd:011228128:mpeg21:p001:a0001:zoning">
								<didl:Descriptor>
									<didl:Statement mimeType="text/plain" dc:type="role">metadata/zoning</didl:Statement>
								</didl:Descriptor>
								<didl:Resource mimeType="text/xml">
									<dcx:zoning>
										<dcx:coordinates image="DDD_011228128_001_access.jp2">
											<dcx:area hpos="253" vpos="527" width="716" height="45"/>
											<dcx:area hpos="102" vpos="582" width="1052" height="1245"/>
										</dcx:coordinates>
									</dcx:zoning>
								</didl:Resource>
							</didl:Component>
						</didl:Item>
						<didl:Item dc:identifier="ddd:011228128:mpeg21:p001:a0002" ddd:article_id="ddd:011228128:mpeg21:a0002">
							<didl:Component dc:identifier="ddd:011228128:mpeg21:p001:a0002:metadata">
								<didl:Descriptor>
									<didl:Statement mimeType="text/plain" dc:type="role">metadata</didl:Statement>
								</didl:Descriptor>
								<didl:Resource mimeType="text/xml">
									<srw_dc:dcx>
										<dc:subject>artikel</dc:subject>
										<dc:title>ITALIEN</dc:title>
										<dcterms:accessRights>accessible</dcterms:accessRights>
										<dcx:recordIdentifier>ddd:011228128:mpeg21:a0002</dcx:recordIdentifier>
										<dc:identifier>http://resolver.kb.nl/resolve?urn=ddd:011228128:mpeg21:a0002</dc:identifier>
										<dc:type xsi:type="dcterms:DCMIType">Text</dc:type>
									</srw_dc:dcx>
								</didl:Resource>
							</didl:Component>
							<didl:Component dc:identifier="ddd:011228128:mpeg21:p001:a0002:zoning">
								<didl:Descriptor>
									<didl:Statement mimeType="text/plain" dc:type="role">metadata/zoning</didl:Statement>
								</didl:Descriptor>
								<didl:Resource mimeType="text/xml">
									<dcx:zoning>
										<dcx:coordinates image="DDD_011228128_001_access.jp2">
											<dcx:area hpos="337" vpos="1831" width="565" height="50"/>
											<dcx:area hpos="110" vpos="1883" width="1057" height="1448"/>
										</dcx:coordinates>
									</dcx:zoning>
								</didl:Resource>
							</didl:Component>
						</didl:Item>
						<didl:Item dc:identifier="ddd:011228128:mpeg21:p001:a0003" ddd:article_id="ddd:011228128:mpeg21:a0003">
							<didl:Component dc:identifier="ddd:011228128:mpeg21:p001:a0003:metadata">
								<didl:Descriptor>
									<didl:Statement mimeType="text/plain" dc:type="role">metadata</didl:Statement>
								</didl:Descriptor>
								<didl:Resource mimeType="text/xml">
									<srw_dc:dcx>
										<dc:subject>artikel</dc:subject>
										<dc:title>SWITSERLANT</dc:title>
										<dcterms:accessRights>accessible</dcterms:accessRights>
										<dcx:recordIdentifier>ddd:011228128:mpeg21:a0003</dcx:recordIdentifier>
										<dc:identifier>http://resolver.kb.nl/resolve?urn=ddd:011228128:mpeg21:a0003</dc:identifier>
										<dc:type xsi:type="dcterms:DCMIType">Text</dc:type>
									</srw_dc:dcx>
								</didl:Resource>
							</didl:Component>
							<didl:Component dc:identifier="ddd:011228128:mpeg21:p001:a0003:zoning">
								<didl:Descriptor>
									<didl:Statement mimeType="text/plain" dc:type="role">metadata/zoning</didl:Statement>
								</didl:Descriptor>
								<didl:Resource mimeType="text/xml">
									<dcx:zoning>
										<dcx:coordinates image="DDD_011228128_001_access.jp2">
											<dcx:area hpos="110" vpos="3330" width="1058" height="57"/>
											<dcx:area hpos="110" vpos="3385" width="1058" height="1042"/>
											<dcx:area hpos="1187" vpos="516" width="1056" height="293"/>
										</dcx:coordinates>
									</dcx:zoning>
								</didl:Resource>
							</didl:Component>
						</didl:Item>
						<didl:Item dc:identifier="ddd:011228128:mpeg21:p001:a0004" ddd:article_id="ddd:011228128:mpeg21:a0004">
							<didl:Component dc:identifier="ddd:011228128:mpeg21:p001:a0004:metadata">
								<didl:Descriptor>
									<didl:Statement mimeType="text/plain" dc:type="role">metadata</didl:Statement>
								</didl:Descriptor>
								<didl:Resource mimeType="text/xml">
									<srw_dc:dcx>
										<dc:subject>artikel</dc:subject>
										<dc:title>Duytfant en d'aengrenfende Rijcken.</dc:title>
										<dcterms:accessRights>accessible</dcterms:accessRights>
										<dcx:recordIdentifier>ddd:011228128:mpeg21:a0004</dcx:recordIdentifier>
										<dc:identifier>http://resolver.kb.nl/resolve?urn=ddd:011228128:mpeg21:a0004</dc:identifier>
										<dc:type xsi:type="dcterms:DCMIType">Text</dc:type>
									</srw_dc:dcx>
								</didl:Resource>
							</didl:Component>
							<didl:Component dc:identifier="ddd:011228128:mpeg21:p001:a0004:zoning">
								<didl:Descriptor>
									<didl:Statement mimeType="text/plain" dc:type="role">metadata/zoning</didl:Statement>
								</didl:Descriptor>
								<didl:Resource mimeType="text/xml">
									<dcx:zoning>
										<dcx:coordinates image="DDD_011228128_001_access.jp2">
											<dcx:area hpos="1243" vpos="808" width="987" height="48"/>
											<dcx:area hpos="1187" vpos="855" width="1059" height="2692"/>
										</dcx:coordinates>
									</dcx:zoning>
								</didl:Resource>
							</didl:Component>
						</didl:Item>
						<didl:Item dc:identifier="ddd:011228128:mpeg21:p001:a0005" ddd:article_id="ddd:011228128:mpeg21:a0005">
							<didl:Component dc:identifier="ddd:011228128:mpeg21:p001:a0005:metadata">
								<didl:Descriptor>
									<didl:Statement mimeType="text/plain" dc:type="role">metadata</didl:Statement>
								</didl:Descriptor>
								<didl:Resource mimeType="text/xml">
									<srw_dc:dcx>
										<dc:subject>artikel</dc:subject>
										<dc:title>NEDERLANDEN</dc:title>
										<dcterms:accessRights>accessible</dcterms:accessRights>
										<dcx:recordIdentifier>ddd:011228128:mpeg21:a0005</dcx:recordIdentifier>
										<dc:identifier>http://resolver.kb.nl/resolve?urn=ddd:011228128:mpeg21:a0005</dc:identifier>
										<dc:type xsi:type="dcterms:DCMIType">Text</dc:type>
									</srw_dc:dcx>
								</didl:Resource>
							</didl:Component>
							<didl:Component dc:identifier="ddd:011228128:mpeg21:p001:a0005:zoning">
								<didl:Descriptor>
									<didl:Statement mimeType="text/plain" dc:type="role">metadata/zoning</didl:Statement>
								</didl:Descriptor>
								<didl:Resource mimeType="text/xml">
									<dcx:zoning>
										<dcx:coordinates image="DDD_011228128_001_access.jp2">
											<dcx:area hpos="1187" vpos="3546" width="1059" height="56"/>
											<dcx:area hpos="1187" vpos="3600" width="1060" height="786"/>
										</dcx:coordinates>
									</dcx:zoning>
								</didl:Resource>
							</didl:Component>
						</didl:Item>
					</didl:Item>
					<didl:Item dc:identifier="ddd:011228128:mpeg21:p002">
						<didl:Descriptor>
							<didl:Statement mimeType="text/plain" dc:type="role">page 2</didl:Statement>
						</didl:Descriptor>
						<didl:Component dc:identifier="ddd:011228128:mpeg21:p002:metadata">
							<didl:Descriptor>
								<didl:Statement mimeType="text/plain" dc:type="role">metadata</didl:Statement>
							</didl:Descriptor>
							<didl:Resource mimeType="text/xml">
								<srw_dc:dcx>
									<ddd:nativePageNumber>2</ddd:nativePageNumber>
									<dcx:recordIdentifier>ddd:011228128:mpeg21:p002</dcx:recordIdentifier>
									<dc:identifier>http://resolver.kb.nl/resolve?urn=ddd:011228128:mpeg21:p002</dc:identifier>
									<dc:type xsi:type="dcterms:DCMIType">Text</dc:type>
								<ddd:OCRConfidencelevel>0.626</ddd:OCRConfidencelevel></srw_dc:dcx>
							</didl:Resource>
						</didl:Component>
						<didl:Component dc:identifier="ddd:011228128:mpeg21:p002:image/preservation">
							<didl:Descriptor>
								<didl:Statement mimeType="text/plain" dc:type="role">image/preservation</didl:Statement>
							</didl:Descriptor>
							<didl:Resource mimeType="image/jp2" ref="DDD_011228128_002.jp2" dcx:md5_checksum="4169e4fa53533aca53a21f1cb6468c5f"/>
						</didl:Component>
						<didl:Component dc:identifier="ddd:011228128:mpeg21:p002:metadata/technical">
							<didl:Descriptor>
								<didl:Statement mimeType="text/plain" dc:type="role">metadata/technical</didl:Statement>
							</didl:Descriptor>
							<didl:Resource mimeType="text/xml" ref="DDD_011228128_002_techmeta.xml" dcx:md5_checksum="19ad6ea4e116ca35674d8a9e6873618f"/>
						</didl:Component>
						<didl:Component dc:identifier="ddd:011228128:mpeg21:p002:image">
							<didl:Descriptor>
								<didl:Statement mimeType="text/plain" dc:type="role">image</didl:Statement>
							</didl:Descriptor>
							<didl:Resource mimeType="image/jp2" ref="http://resolver.kb.nl/resolve?urn=ddd:011228128:mpeg21:p002:image" dcx:filename="DDD_011228128_002_access.jp2" dcx:md5_checksum="50e21ce96f65bbcc829d586398446948"/>
						</didl:Component>
						<didl:Component dc:identifier="ddd:011228128:mpeg21:p002:alto">
							<didl:Descriptor>
								<didl:Statement mimeType="text/plain" dc:type="role">alto</didl:Statement>
							</didl:Descriptor>
							<didl:Resource mimeType="text/xml" ref="http://resolver.kb.nl/resolve?urn=ddd:011228128:mpeg21:p002:alto" dcx:filename="DDD_011228128_002_alto.xml" dcx:md5_checksum="9f23c18cff4c8ce09e6d62bd96f95298"/>
						</didl:Component>
						<didl:Item dc:identifier="ddd:011228128:mpeg21:p002:a0001" ddd:article_id="ddd:011228128:mpeg21:a0005">
							<didl:Component dc:identifier="ddd:011228128:mpeg21:p002:a0001:metadata">
								<didl:Descriptor>
									<didl:Statement mimeType="text/plain" dc:type="role">metadata</didl:Statement>
								</didl:Descriptor>
								<didl:Resource mimeType="text/xml">
									<srw_dc:dcx>
										<dc:subject>artikel</dc:subject>
										<dc:title>NEDERLANDEN</dc:title>
										<dcterms:accessRights>accessible</dcterms:accessRights>
										<dcx:recordIdentifier>ddd:011228128:mpeg21:a0005</dcx:recordIdentifier>
										<dc:identifier>http://resolver.kb.nl/resolve?urn=ddd:011228128:mpeg21:a0005</dc:identifier>
										<dc:type xsi:type="dcterms:DCMIType">Text</dc:type>
									</srw_dc:dcx>
								</didl:Resource>
							</didl:Component>
							<didl:Component dc:identifier="ddd:011228128:mpeg21:p002:a0001:zoning">
								<didl:Descriptor>
									<didl:Statement mimeType="text/plain" dc:type="role">metadata/zoning</didl:Statement>
								</didl:Descriptor>
								<didl:Resource mimeType="text/xml">
									<dcx:zoning>
										<dcx:coordinates image="DDD_011228128_002_access.jp2">
											<dcx:area hpos="180" vpos="71" width="1076" height="1886"/>
										</dcx:coordinates>
									</dcx:zoning>
								</didl:Resource>
							</didl:Component>
						</didl:Item>
						<didl:Item dc:identifier="ddd:011228128:mpeg21:p002:a0002" ddd:article_id="ddd:011228128:mpeg21:a0006">
							<didl:Component dc:identifier="ddd:011228128:mpeg21:p002:a0002:metadata">
								<didl:Descriptor>
									<didl:Statement mimeType="text/plain" dc:type="role">metadata</didl:Statement>
								</didl:Descriptor>
								<didl:Resource mimeType="text/xml">
									<srw_dc:dcx>
										<dc:subject>artikel</dc:subject>
										<dc:title>Parijs den 10 Maett.Te Port-Louys is het Schip Aichion uytweft-</dc:title>
										<dcterms:accessRights>accessible</dcterms:accessRights>
										<dcx:recordIdentifier>ddd:011228128:mpeg21:a0006</dcx:recordIdentifier>
										<dc:identifier>http://resolver.kb.nl/resolve?urn=ddd:011228128:mpeg21:a0006</dc:identifier>
										<dc:type xsi:type="dcterms:DCMIType">Text</dc:type>
									</srw_dc:dcx>
								</didl:Resource>
							</didl:Component>
							<didl:Component dc:identifier="ddd:011228128:mpeg21:p002:a0002:zoning">
								<didl:Descriptor>
									<didl:Statement mimeType="text/plain" dc:type="role">metadata/zoning</didl:Statement>
								</didl:Descriptor>
								<didl:Resource mimeType="text/xml">
									<dcx:zoning>
										<dcx:coordinates image="DDD_011228128_002_access.jp2">
											<dcx:area hpos="180" vpos="1956" width="1076" height="154"/>
											<dcx:area hpos="1253" vpos="71" width="1075" height="2037"/>
										</dcx:coordinates>
									</dcx:zoning>
								</didl:Resource>
							</didl:Component>
						</didl:Item>
						<didl:Item dc:identifier="ddd:011228128:mpeg21:p002:a0003" ddd:article_id="ddd:011228128:mpeg21:a0007">
							<didl:Component dc:identifier="ddd:011228128:mpeg21:p002:a0003:metadata">
								<didl:Descriptor>
									<didl:Statement mimeType="text/plain" dc:type="role">metadata</didl:Statement>
								</didl:Descriptor>
								<didl:Resource mimeType="text/xml">
									<srw_dc:dcx>
										<dc:subject>advertentie</dc:subject>
										<dc:title>Advertentie</dc:title>
										<dcterms:accessRights>accessible</dcterms:accessRights>
										<dcx:recordIdentifier>ddd:011228128:mpeg21:a0007</dcx:recordIdentifier>
										<dc:identifier>http://resolver.kb.nl/resolve?urn=ddd:011228128:mpeg21:a0007</dc:identifier>
										<dc:type xsi:type="dcterms:DCMIType">Text</dc:type>
									</srw_dc:dcx>
								</didl:Resource>
							</didl:Component>
							<didl:Component dc:identifier="ddd:011228128:mpeg21:p002:a0003:zoning">
								<didl:Descriptor>
									<didl:Statement mimeType="text/plain" dc:type="role">metadata/zoning</didl:Statement>
								</didl:Descriptor>
								<didl:Resource mimeType="text/xml">
									<dcx:zoning>
										<dcx:coordinates image="DDD_011228128_002_access.jp2">
											<dcx:area hpos="24" vpos="2106" width="2303" height="2425"/>
										</dcx:coordinates>
									</dcx:zoning>
								</didl:Resource>
							</didl:Component>
						</didl:Item>
					</didl:Item>
					<didl:Item dc:identifier="ddd:011228128:mpeg21:a0001">
						<didl:Descriptor>
							<didl:Statement mimeType="text/plain" dc:type="role">article 1</didl:Statement>
						</didl:Descriptor>
						<didl:Component dc:identifier="ddd:011228128:mpeg21:a0001:ocr">
							<didl:Descriptor>
								<didl:Statement mimeType="text/plain" dc:type="role">ocr</didl:Statement>
							</didl:Descriptor>
							<didl:Resource mimeType="text/xml" ref="http://resolver.kb.nl/resolve?urn=ddd:011228128:mpeg21:a0001:ocr" dcx:filename="DDD_011228128_0001_articletext.xml" dcx:md5_checksum="75f4044eb4bd2db4a09b8fdf63972c54"/>
						</didl:Component>
						<didl:Component dc:identifier="ddd:011228128:mpeg21:a0001:metadata">
							<didl:Descriptor>
								<didl:Statement mimeType="text/plain" dc:type="role">metadata</didl:Statement>
							</didl:Descriptor>
							<didl:Resource mimeType="text/xml">
								<srw_dc:dcx>
									<dc:subject>artikel</dc:subject>
									<dc:title>TURCKYEN</dc:title>
									<dcterms:accessRights>accessible</dcterms:accessRights>
									<dcx:recordIdentifier>ddd:011228128:mpeg21:a0001</dcx:recordIdentifier>
									<dc:identifier>http://resolver.kb.nl/resolve?urn=ddd:011228128:mpeg21:a0001</dc:identifier>
									<dc:type xsi:type="dcterms:DCMIType">Text</dc:type>
								</srw_dc:dcx>
							</didl:Resource>
						</didl:Component>
						<didl:Component dc:identifier="ddd:011228128:mpeg21:a0001:zoning">
							<didl:Descriptor>
								<didl:Statement mimeType="text/plain" dc:type="role">metadata/zoning</didl:Statement>
							</didl:Descriptor>
							<didl:Resource mimeType="text/xml">
								<dcx:zoning>
									<dcx:article-part order="1" pageid="ddd:011228128:mpeg21:p001">
										<dcx:coordinates image="DDD_011228128_001_access.jp2">
											<dcx:area hpos="253" vpos="527" width="716" height="45"/>
											<dcx:area hpos="102" vpos="582" width="1052" height="1245"/>
										</dcx:coordinates>
										<dcx:blocks alto="DDD_011228128_001_alto.xml">
											<dcx:TextBlock ID="P1_TB00003"/>
											<dcx:TextBlock ID="P1_TB00004"/>
										</dcx:blocks>
									</dcx:article-part>
								</dcx:zoning>
							</didl:Resource>
						</didl:Component>
					</didl:Item>
					<didl:Item dc:identifier="ddd:011228128:mpeg21:a0002">
						<didl:Descriptor>
							<didl:Statement mimeType="text/plain" dc:type="role">article 2</didl:Statement>
						</didl:Descriptor>
						<didl:Component dc:identifier="ddd:011228128:mpeg21:a0002:ocr">
							<didl:Descriptor>
								<didl:Statement mimeType="text/plain" dc:type="role">ocr</didl:Statement>
							</didl:Descriptor>
							<didl:Resource mimeType="text/xml" ref="http://resolver.kb.nl/resolve?urn=ddd:011228128:mpeg21:a0002:ocr" dcx:filename="DDD_011228128_0002_articletext.xml" dcx:md5_checksum="fa81d76205b7df17cf5f08400d1570a3"/>
						</didl:Component>
						<didl:Component dc:identifier="ddd:011228128:mpeg21:a0002:metadata">
							<didl:Descriptor>
								<didl:Statement mimeType="text/plain" dc:type="role">metadata</didl:Statement>
							</didl:Descriptor>
							<didl:Resource mimeType="text/xml">
								<srw_dc:dcx>
									<dc:subject>artikel</dc:subject>
									<dc:title>ITALIEN</dc:title>
									<dcterms:accessRights>accessible</dcterms:accessRights>
									<dcx:recordIdentifier>ddd:011228128:mpeg21:a0002</dcx:recordIdentifier>
									<dc:identifier>http://resolver.kb.nl/resolve?urn=ddd:011228128:mpeg21:a0002</dc:identifier>
									<dc:type xsi:type="dcterms:DCMIType">Text</dc:type>
								</srw_dc:dcx>
							</didl:Resource>
						</didl:Component>
						<didl:Component dc:identifier="ddd:011228128:mpeg21:a0002:zoning">
							<didl:Descriptor>
								<didl:Statement mimeType="text/plain" dc:type="role">metadata/zoning</didl:Statement>
							</didl:Descriptor>
							<didl:Resource mimeType="text/xml">
								<dcx:zoning>
									<dcx:article-part order="1" pageid="ddd:011228128:mpeg21:p001">
										<dcx:coordinates image="DDD_011228128_001_access.jp2">
											<dcx:area hpos="337" vpos="1831" width="565" height="50"/>
											<dcx:area hpos="110" vpos="1883" width="1057" height="1448"/>
										</dcx:coordinates>
										<dcx:blocks alto="DDD_011228128_001_alto.xml">
											<dcx:TextBlock ID="P1_TB00005"/>
											<dcx:TextBlock ID="P1_TB00006"/>
										</dcx:blocks>
									</dcx:article-part>
								</dcx:zoning>
							</didl:Resource>
						</didl:Component>
					</didl:Item>
					<didl:Item dc:identifier="ddd:011228128:mpeg21:a0003">
						<didl:Descriptor>
							<didl:Statement mimeType="text/plain" dc:type="role">article 3</didl:Statement>
						</didl:Descriptor>
						<didl:Component dc:identifier="ddd:011228128:mpeg21:a0003:ocr">
							<didl:Descriptor>
								<didl:Statement mimeType="text/plain" dc:type="role">ocr</didl:Statement>
							</didl:Descriptor>
							<didl:Resource mimeType="text/xml" ref="http://resolver.kb.nl/resolve?urn=ddd:011228128:mpeg21:a0003:ocr" dcx:filename="DDD_011228128_0003_articletext.xml" dcx:md5_checksum="c907a0ae3ca43ae04ae58a2b35e2de23"/>
						</didl:Component>
						<didl:Component dc:identifier="ddd:011228128:mpeg21:a0003:metadata">
							<didl:Descriptor>
								<didl:Statement mimeType="text/plain" dc:type="role">metadata</didl:Statement>
							</didl:Descriptor>
							<didl:Resource mimeType="text/xml">
								<srw_dc:dcx>
									<dc:subject>artikel</dc:subject>
									<dc:title>SWITSERLANT</dc:title>
									<dcterms:accessRights>accessible</dcterms:accessRights>
									<dcx:recordIdentifier>ddd:011228128:mpeg21:a0003</dcx:recordIdentifier>
									<dc:identifier>http://resolver.kb.nl/resolve?urn=ddd:011228128:mpeg21:a0003</dc:identifier>
									<dc:type xsi:type="dcterms:DCMIType">Text</dc:type>
								</srw_dc:dcx>
							</didl:Resource>
						</didl:Component>
						<didl:Component dc:identifier="ddd:011228128:mpeg21:a0003:zoning">
							<didl:Descriptor>
								<didl:Statement mimeType="text/plain" dc:type="role">metadata/zoning</didl:Statement>
							</didl:Descriptor>
							<didl:Resource mimeType="text/xml">
								<dcx:zoning>
									<dcx:article-part order="1" pageid="ddd:011228128:mpeg21:p001">
										<dcx:coordinates image="DDD_011228128_001_access.jp2">
											<dcx:area hpos="110" vpos="3330" width="1058" height="57"/>
											<dcx:area hpos="110" vpos="3385" width="1058" height="1042"/>
											<dcx:area hpos="1187" vpos="516" width="1056" height="293"/>
										</dcx:coordinates>
										<dcx:blocks alto="DDD_011228128_001_alto.xml">
											<dcx:TextBlock ID="P1_TB00007"/>
											<dcx:TextBlock ID="P1_TB00008"/>
											<dcx:TextBlock ID="P1_TB00009"/>
										</dcx:blocks>
									</dcx:article-part>
								</dcx:zoning>
							</didl:Resource>
						</didl:Component>
					</didl:Item>
					<didl:Item dc:identifier="ddd:011228128:mpeg21:a0004">
						<didl:Descriptor>
							<didl:Statement mimeType="text/plain" dc:type="role">article 4</didl:Statement>
						</didl:Descriptor>
						<didl:Component dc:identifier="ddd:011228128:mpeg21:a0004:ocr">
							<didl:Descriptor>
								<didl:Statement mimeType="text/plain" dc:type="role">ocr</didl:Statement>
							</didl:Descriptor>
							<didl:Resource mimeType="text/xml" ref="http://resolver.kb.nl/resolve?urn=ddd:011228128:mpeg21:a0004:ocr" dcx:filename="DDD_011228128_0004_articletext.xml" dcx:md5_checksum="2bde370d984319622a23b5a07e7a1bd5"/>
						</didl:Component>
						<didl:Component dc:identifier="ddd:011228128:mpeg21:a0004:metadata">
							<didl:Descriptor>
								<didl:Statement mimeType="text/plain" dc:type="role">metadata</didl:Statement>
							</didl:Descriptor>
							<didl:Resource mimeType="text/xml">
								<srw_dc:dcx>
									<dc:subject>artikel</dc:subject>
									<dc:title>Duytfant en d'aengrenfende Rijcken.</dc:title>
									<dcterms:accessRights>accessible</dcterms:accessRights>
									<dcx:recordIdentifier>ddd:011228128:mpeg21:a0004</dcx:recordIdentifier>
									<dc:identifier>http://resolver.kb.nl/resolve?urn=ddd:011228128:mpeg21:a0004</dc:identifier>
									<dc:type xsi:type="dcterms:DCMIType">Text</dc:type>
								</srw_dc:dcx>
							</didl:Resource>
						</didl:Component>
						<didl:Component dc:identifier="ddd:011228128:mpeg21:a0004:zoning">
							<didl:Descriptor>
								<didl:Statement mimeType="text/plain" dc:type="role">metadata/zoning</didl:Statement>
							</didl:Descriptor>
							<didl:Resource mimeType="text/xml">
								<dcx:zoning>
									<dcx:article-part order="1" pageid="ddd:011228128:mpeg21:p001">
										<dcx:coordinates image="DDD_011228128_001_access.jp2">
											<dcx:area hpos="1243" vpos="808" width="987" height="48"/>
											<dcx:area hpos="1187" vpos="855" width="1059" height="2692"/>
										</dcx:coordinates>
										<dcx:blocks alto="DDD_011228128_001_alto.xml">
											<dcx:TextBlock ID="P1_TB00010"/>
											<dcx:TextBlock ID="P1_TB00011"/>
										</dcx:blocks>
									</dcx:article-part>
								</dcx:zoning>
							</didl:Resource>
						</didl:Component>
					</didl:Item>
					<didl:Item dc:identifier="ddd:011228128:mpeg21:a0005">
						<didl:Descriptor>
							<didl:Statement mimeType="text/plain" dc:type="role">article 5</didl:Statement>
						</didl:Descriptor>
						<didl:Component dc:identifier="ddd:011228128:mpeg21:a0005:ocr">
							<didl:Descriptor>
								<didl:Statement mimeType="text/plain" dc:type="role">ocr</didl:Statement>
							</didl:Descriptor>
							<didl:Resource mimeType="text/xml" ref="http://resolver.kb.nl/resolve?urn=ddd:011228128:mpeg21:a0005:ocr" dcx:filename="DDD_011228128_0005_articletext.xml" dcx:md5_checksum="8222d2f2f335344bc50b41c5111698fd"/>
						</didl:Component>
						<didl:Component dc:identifier="ddd:011228128:mpeg21:a0005:metadata">
							<didl:Descriptor>
								<didl:Statement mimeType="text/plain" dc:type="role">metadata</didl:Statement>
							</didl:Descriptor>
							<didl:Resource mimeType="text/xml">
								<srw_dc:dcx>
									<dc:subject>artikel</dc:subject>
									<dc:title>NEDERLANDEN</dc:title>
									<dcterms:accessRights>accessible</dcterms:accessRights>
									<dcx:recordIdentifier>ddd:011228128:mpeg21:a0005</dcx:recordIdentifier>
									<dc:identifier>http://resolver.kb.nl/resolve?urn=ddd:011228128:mpeg21:a0005</dc:identifier>
									<dc:type xsi:type="dcterms:DCMIType">Text</dc:type>
								</srw_dc:dcx>
							</didl:Resource>
						</didl:Component>
						<didl:Component dc:identifier="ddd:011228128:mpeg21:a0005:zoning">
							<didl:Descriptor>
								<didl:Statement mimeType="text/plain" dc:type="role">metadata/zoning</didl:Statement>
							</didl:Descriptor>
							<didl:Resource mimeType="text/xml">
								<dcx:zoning>
									<dcx:article-part order="1" pageid="ddd:011228128:mpeg21:p001">
										<dcx:coordinates image="DDD_011228128_001_access.jp2">
											<dcx:area hpos="1187" vpos="3546" width="1059" height="56"/>
											<dcx:area hpos="1187" vpos="3600" width="1060" height="786"/>
										</dcx:coordinates>
										<dcx:blocks alto="DDD_011228128_001_alto.xml">
											<dcx:TextBlock ID="P1_TB00012"/>
											<dcx:TextBlock ID="P1_TB00013"/>
										</dcx:blocks>
									</dcx:article-part>
									<dcx:article-part order="2" pageid="ddd:011228128:mpeg21:p002">
										<dcx:coordinates image="DDD_011228128_002_access.jp2">
											<dcx:area hpos="180" vpos="71" width="1076" height="1886"/>
										</dcx:coordinates>
										<dcx:blocks alto="DDD_011228128_002_alto.xml">
											<dcx:TextBlock ID="P2_TB00001"/>
										</dcx:blocks>
									</dcx:article-part>
								</dcx:zoning>
							</didl:Resource>
						</didl:Component>
					</didl:Item>
					<didl:Item dc:identifier="ddd:011228128:mpeg21:a0006">
						<didl:Descriptor>
							<didl:Statement mimeType="text/plain" dc:type="role">article 6</didl:Statement>
						</didl:Descriptor>
						<didl:Component dc:identifier="ddd:011228128:mpeg21:a0006:ocr">
							<didl:Descriptor>
								<didl:Statement mimeType="text/plain" dc:type="role">ocr</didl:Statement>
							</didl:Descriptor>
							<didl:Resource mimeType="text/xml" ref="http://resolver.kb.nl/resolve?urn=ddd:011228128:mpeg21:a0006:ocr" dcx:filename="DDD_011228128_0006_articletext.xml" dcx:md5_checksum="794e40ccf972c99ae4094f34406b0c53"/>
						</didl:Component>
						<didl:Component dc:identifier="ddd:011228128:mpeg21:a0006:metadata">
							<didl:Descriptor>
								<didl:Statement mimeType="text/plain" dc:type="role">metadata</didl:Statement>
							</didl:Descriptor>
							<didl:Resource mimeType="text/xml">
								<srw_dc:dcx>
									<dc:subject>artikel</dc:subject>
									<dc:title>Parijs den 10 Maett.Te Port-Louys is het Schip Aichion uytweft-</dc:title>
									<dcterms:accessRights>accessible</dcterms:accessRights>
									<dcx:recordIdentifier>ddd:011228128:mpeg21:a0006</dcx:recordIdentifier>
									<dc:identifier>http://resolver.kb.nl/resolve?urn=ddd:011228128:mpeg21:a0006</dc:identifier>
									<dc:type xsi:type="dcterms:DCMIType">Text</dc:type>
								</srw_dc:dcx>
							</didl:Resource>
						</didl:Component>
						<didl:Component dc:identifier="ddd:011228128:mpeg21:a0006:zoning">
							<didl:Descriptor>
								<didl:Statement mimeType="text/plain" dc:type="role">metadata/zoning</didl:Statement>
							</didl:Descriptor>
							<didl:Resource mimeType="text/xml">
								<dcx:zoning>
									<dcx:article-part order="1" pageid="ddd:011228128:mpeg21:p002">
										<dcx:coordinates image="DDD_011228128_002_access.jp2">
											<dcx:area hpos="180" vpos="1956" width="1076" height="154"/>
											<dcx:area hpos="1253" vpos="71" width="1075" height="2037"/>
										</dcx:coordinates>
										<dcx:blocks alto="DDD_011228128_002_alto.xml">
											<dcx:TextBlock ID="P2_TB00002"/>
											<dcx:TextBlock ID="P2_TB00003"/>
										</dcx:blocks>
									</dcx:article-part>
								</dcx:zoning>
							</didl:Resource>
						</didl:Component>
					</didl:Item>
					<didl:Item dc:identifier="ddd:011228128:mpeg21:a0007">
						<didl:Descriptor>
							<didl:Statement mimeType="text/plain" dc:type="role">article 7</didl:Statement>
						</didl:Descriptor>
						<didl:Component dc:identifier="ddd:011228128:mpeg21:a0007:ocr">
							<didl:Descriptor>
								<didl:Statement mimeType="text/plain" dc:type="role">ocr</didl:Statement>
							</didl:Descriptor>
							<didl:Resource mimeType="text/xml" ref="http://resolver.kb.nl/resolve?urn=ddd:011228128:mpeg21:a0007:ocr" dcx:filename="DDD_011228128_0007_articletext.xml" dcx:md5_checksum="45fe9966c877b95a853a44e2194da785"/>
						</didl:Component>
						<didl:Component dc:identifier="ddd:011228128:mpeg21:a0007:metadata">
							<didl:Descriptor>
								<didl:Statement mimeType="text/plain" dc:type="role">metadata</didl:Statement>
							</didl:Descriptor>
							<didl:Resource mimeType="text/xml">
								<srw_dc:dcx>
									<dc:subject>advertentie</dc:subject>
									<dc:title>Advertentie</dc:title>
									<dcterms:accessRights>accessible</dcterms:accessRights>
									<dcx:recordIdentifier>ddd:011228128:mpeg21:a0007</dcx:recordIdentifier>
									<dc:identifier>http://resolver.kb.nl/resolve?urn=ddd:011228128:mpeg21:a0007</dc:identifier>
									<dc:type xsi:type="dcterms:DCMIType">Text</dc:type>
								</srw_dc:dcx>
							</didl:Resource>
						</didl:Component>
						<didl:Component dc:identifier="ddd:011228128:mpeg21:a0007:zoning">
							<didl:Descriptor>
								<didl:Statement mimeType="text/plain" dc:type="role">metadata/zoning</didl:Statement>
							</didl:Descriptor>
							<didl:Resource mimeType="text/xml">
								<dcx:zoning>
									<dcx:article-part order="1" pageid="ddd:011228128:mpeg21:p002">
										<dcx:coordinates image="DDD_011228128_002_access.jp2">
											<dcx:area hpos="24" vpos="2106" width="2303" height="2425"/>
										</dcx:coordinates>
										<dcx:blocks alto="DDD_011228128_002_alto.xml">
											<dcx:TextBlock ID="P2_TB00004"/>
										</dcx:blocks>
									</dcx:article-part>
								</dcx:zoning>
							</didl:Resource>
						</didl:Component>
					</didl:Item>
				</didl:Item>
			</didl:DIDL>